LICENSE
MANIFEST.in
README.rst
apyclient.py
setup.py
test_apyclient.py
apyclient.egg-info/PKG-INFO
apyclient.egg-info/SOURCES.txt
apyclient.egg-info/dependency_links.txt
apyclient.egg-info/not-zip-safe
apyclient.egg-info/requires.txt
apyclient.egg-info/top_level.txt